Metadata-Version: 2.1
Name: divine
Version: 0.0.1
Summary: Configuration tool
Home-page: UNKNOWN
Author: Jim Kitchen
Author-email: jim22k@gmail.com
License: UNKNOWN
Platform: UNKNOWN
Classifier: Programming Language :: Python :: 3
Classifier: Operating System :: OS Independent
